duckdq/__init__.py
duckdq/client.py
duckdq-0.0.7.dist-info/METADATA
duckdq-0.0.7.dist-info/WHEEL
duckdq-0.0.7.dist-info/top_level.txt
duckdq-0.0.7.dist-info/RECORD
