Metadata-Version: 2.1
Name: duckdq
Version: 0.0.7
Summary: A DQ package
Author-email: Brian Mearns <brian.mearns@gmail.com>
Project-URL: Homepage, https://github.com/mearnsb/api-client
Project-URL: Issues, https://github.com/mearnsb/api-client/issues
Classifier: Programming Language :: Python :: 3
Classifier: Operating System :: OS Independent
Requires-Python: >=3.8
Requires-Dist: pandas ==2.2.2
Requires-Dist: duckdb ==1.1.0
Requires-Dist: supabase ==2.7.4
Requires-Dist: python-dotenv ==1.0.1
